rf2rnd/__init__.py
rf2rnd/collector.py
rf2rnd/extractor.py
rf2rnd/generator.py
tests/__init__.py
tests/test_0.py
tests/test_cum_sum.py
tests/test_monobit.py
tests/test_rand_excursion.py
rf2rnd-0.1.0.dist-info/METADATA
rf2rnd-0.1.0.dist-info/WHEEL
rf2rnd-0.1.0.dist-info/top_level.txt
rf2rnd-0.1.0.dist-info/RECORD
