Metadata-Version: 2.1
Name: rf2rnd
Version: 0.1.0
Summary: RF noise to random number generator
Home-page: https://github.com/pyshadi/rf2rnd
Author: Your Name
Author-email: shadi.alhaj.ch@gmail.com
Classifier: Programming Language :: Python :: 3
Classifier: License :: OSI Approved :: MIT License
Classifier: Operating System :: OS Independent
Requires-Python: >=3.6
